financiallib/__init__.py
financiallib/chartpack.py
financiallib/finstats.py
financiallib/new_optimizers.py
financiallib/optimizers.py
financiallib/plots.py
financiallib/statistical_tests.py
financiallib/technical_indicators.py
financiallib/utils.py
financiallib-2.0.3.dist-info/LICENSE.txt
financiallib-2.0.3.dist-info/METADATA
financiallib-2.0.3.dist-info/WHEEL
financiallib-2.0.3.dist-info/top_level.txt
financiallib-2.0.3.dist-info/RECORD
